abvio/__init__.py
abvio/cli.py
abvio/incar.py
abvio/io.py
abvio/kpoints.py
abvio/structure.py
abvio-0.0.1.dist-info/LICENSE
abvio-0.0.1.dist-info/METADATA
abvio-0.0.1.dist-info/WHEEL
abvio-0.0.1.dist-info/entry_points.txt
abvio-0.0.1.dist-info/top_level.txt
abvio-0.0.1.dist-info/RECORD
