Metadata-Version: 2.1
Name: abvio
Version: 0.0.1
Summary: A Python package to simplify VASP input files
Author-email: William Laderer <wtladerer@gmail.com>
Project-URL: Documentation, https://wladerer.github.io/abvio/
Project-URL: Issues, https://github.com/wladerer/abvio/issues
Classifier: Intended Audience :: Science/Research
Classifier: Programming Language :: Python :: 3
Classifier: Topic :: Scientific/Engineering :: Physics
Classifier: Topic :: Scientific/Engineering :: Chemistry
License-File: LICENSE
Requires-Dist: numpy <2
Requires-Dist: pymatgen
Requires-Dist: mp-api
Requires-Dist: pydantic
Requires-Dist: rich
